LICENSE.txt
MANIFEST.in
NOTICE
README.md
setup.cfg
setup.py
apache_superset_db.egg-info/PKG-INFO
apache_superset_db.egg-info/SOURCES.txt
apache_superset_db.egg-info/dependency_links.txt
apache_superset_db.egg-info/entry_points.txt
apache_superset_db.egg-info/not-zip-safe
apache_superset_db.egg-info/requires.txt
apache_superset_db.egg-info/top_level.txt
superset/__init__.py
superset/app.py
superset/config.py
superset/constants.py
superset/dataframe.py
superset/errors.py
superset/exceptions.py
superset/forms.py
superset/jinja_context.py
superset/legacy.py
superset/result_set.py
superset/schemas.py
superset/sql_lab.py
superset/sql_parse.py
superset/stats_logger.py
superset/superset_typing.py
superset/viz.py
superset-frontend/package.json
superset/annotation_layers/__init__.py
superset/annotation_layers/api.py
superset/annotation_layers/dao.py
superset/annotation_layers/filters.py
superset/annotation_layers/schemas.py
superset/annotation_layers/annotations/__init__.py
superset/annotation_layers/annotations/api.py
superset/annotation_layers/annotations/dao.py
superset/annotation_layers/annotations/filters.py
superset/annotation_layers/annotations/schemas.py
superset/annotation_layers/annotations/commands/__init__.py
superset/annotation_layers/annotations/commands/bulk_delete.py
superset/annotation_layers/annotations/commands/create.py
superset/annotation_layers/annotations/commands/delete.py
superset/annotation_layers/annotations/commands/exceptions.py
superset/annotation_layers/annotations/commands/update.py
superset/annotation_layers/commands/__init__.py
superset/annotation_layers/commands/bulk_delete.py
superset/annotation_layers/commands/create.py
superset/annotation_layers/commands/delete.py
superset/annotation_layers/commands/exceptions.py
superset/annotation_layers/commands/update.py
superset/async_events/__init__.py
superset/async_events/api.py
superset/cachekeys/__init__.py
superset/cachekeys/api.py
superset/cachekeys/schemas.py
superset/charts/__init__.py
superset/charts/api.py
superset/charts/dao.py
superset/charts/filters.py
superset/charts/post_processing.py
superset/charts/schemas.py
superset/charts/commands/__init__.py
superset/charts/commands/bulk_delete.py
superset/charts/commands/create.py
superset/charts/commands/delete.py
